wario/CustomSettings.py
wario/CustomWidgets.py
wario/GlobalWidgets.py
wario/PipelineThread.py
wario/__init__.py
wario/pipeline/GlobalVar.py
wario/pipeline/JsonInterface.py
wario/pipeline/Node.py
wario/pipeline/NodeFactory.py
wario/pipeline/Pipeline.py
wario/pipeline/__init__.py
WARIO-1.0.dist-info/LICENSE
WARIO-1.0.dist-info/METADATA
WARIO-1.0.dist-info/WHEEL
WARIO-1.0.dist-info/top_level.txt
WARIO-1.0.dist-info/RECORD
