Metadata-Version: 2.1
Name: WARIO
Version: 1.0
Summary: Pipeline backend and node development tools for WARIO
Home-page: https://github.com/McMasterRS/WARIO
Author: Oliver Cook, Thomas Mudway, Ron Harwood
License: UNKNOWN
Platform: UNKNOWN
Classifier: Programming Language :: Python :: 3
Classifier: License :: OSI Approved :: MIT License
Classifier: Operating System :: OS Independent
Requires-Python: >=3.6
Requires-Dist: PyQt5
Requires-Dist: blinker
